make_sst_element/__init__.py
make_sst_element-0.1.3.data/scripts/make-sst-element
make_sst_element-0.1.3.dist-info/LICENSE
make_sst_element-0.1.3.dist-info/METADATA
make_sst_element-0.1.3.dist-info/NOTICE
make_sst_element-0.1.3.dist-info/WHEEL
make_sst_element-0.1.3.dist-info/top_level.txt
make_sst_element-0.1.3.dist-info/RECORD
