Metadata-Version: 2.1
Name: make-sst-element
Version: 0.1.3
Summary: Make an SST Element skeleton repository
Home-page: http://github.com/nicmcd/make-sst-element
Author: Nic McDonald
Author-email: n.mcdonald83@gmail.com
License: BSD
Platform: UNKNOWN
